genophenocorr/__init__.py
genophenocorr/analysis/__init__.py
genophenocorr/analysis/_analyzers.py
genophenocorr/analysis/_inheritance.py
genophenocorr/analysis/_test_fisherExact.py
genophenocorr/analysis/predicate/__init__.py
genophenocorr/analysis/predicate/_all_predicates.py
genophenocorr/analysis/predicate/_api.py
genophenocorr/constants/__init__.py
genophenocorr/constants/variant_effects.py
genophenocorr/data/__init__.py
genophenocorr/data/_toy.py
genophenocorr/model/__init__.py
genophenocorr/model/_cohort.py
genophenocorr/model/_phenotype.py
genophenocorr/model/_protein.py
genophenocorr/model/_variant.py
genophenocorr/preprocessing/__init__.py
genophenocorr/preprocessing/_api.py
genophenocorr/preprocessing/_config.py
genophenocorr/preprocessing/_patient.py
genophenocorr/preprocessing/_phenopacket.py
genophenocorr/preprocessing/_phenotype.py
genophenocorr/preprocessing/_protein.py
genophenocorr/preprocessing/_test_variant.py
genophenocorr/preprocessing/_uniprot.py
genophenocorr/preprocessing/_variant.py
genophenocorr/view/__init__.py
genophenocorr/view/_cohort.py
genophenocorr-0.1.0.dist-info/LICENSE
genophenocorr-0.1.0.dist-info/METADATA
genophenocorr-0.1.0.dist-info/WHEEL
genophenocorr-0.1.0.dist-info/top_level.txt
genophenocorr-0.1.0.dist-info/RECORD
