Metadata-Version: 2.1
Name: genophenocorr
Version: 0.1.0
Summary: Search for genotype-phenotype correlations with GA4GH phenopackets
Author-email: Lauren Rekerle <lauren.rekerle@jax.org>, Daniel Danis <daniel.danis@jax.org>, Peter Robinson <peter.robinson@jax.org>
License: MIT License
Project-URL: homepage, https://github.com/monarch-initiative/genophenocorr
Project-URL: repository, https://github.com/monarch-initiative/genophenocorr.git
Project-URL: documentation, https://monarch-initiative.github.io/genophenocorr/stable
Project-URL: bugtracker, https://github.com/monarch-initiative/genophenocorr/issues
Keywords: Global Alliance for Genomics and Health,GA4GH Phenopacket Schema,Human Phenotype Ontology,GA4GH,Genotype-phenotype correlation,HPO
Classifier: License :: OSI Approved :: MIT License
Classifier: Operating System :: OS Independent
Classifier: Development Status :: 3 - Alpha
Classifier: Programming Language :: Python :: 3.5
Classifier: Intended Audience :: Science/Research
Classifier: Topic :: Scientific/Engineering :: Bio-Informatics
Requires-Python: >=3.5
License-File: LICENSE
Requires-Dist: hpo-toolkit >=0.3.0
Requires-Dist: protobuf >=3.15.0
Requires-Dist: pandas >=2.0.0
Requires-Dist: phenopackets >=2.0.2
Requires-Dist: requests >=2.25.0
Requires-Dist: scipy >=1.11
Requires-Dist: statsmodels >=0.13.0
Requires-Dist: numpy >=1.23
Provides-Extra: docs
Requires-Dist: sphinx >=7.0.0 ; extra == 'docs'
Requires-Dist: sphinx-rtd-theme >=1.3.0 ; extra == 'docs'
Requires-Dist: sphinx-copybutton >=0.5.0 ; extra == 'docs'
Provides-Extra: test
Requires-Dist: pytest >=7.0.0 ; extra == 'test'
